ipyatom/__init__.py
ipyatom/bonds.py
ipyatom/close_neighbour_analysis.py
ipyatom/geometry2d_utils.py
ipyatom/geometry3d_utils.py
ipyatom/plot_mpl.py
ipyatom/render_ivol.py
ipyatom/repeat_cell.py
ipyatom/repeat_density.py
ipyatom/test_bonds.py
ipyatom/test_close_neighbour_analysis.py
ipyatom/test_plot_mpl.py
ipyatom/test_render_ivol.py
ipyatom/test_repeat_cell.py
ipyatom/test_repeat_density.py
ipyatom/test_vacancies.py
ipyatom/transforms.py
ipyatom/utils.py
ipyatom/vacancies.py
ipyatom/validation.py
ipyatom/data/__init__.py
ipyatom/data/atom_data.csv
ipyatom-0.1.0.dist-info/METADATA
ipyatom-0.1.0.dist-info/RECORD
ipyatom-0.1.0.dist-info/WHEEL
ipyatom-0.1.0.dist-info/top_level.txt
ipyatom-0.1.0.dist-info/zip-safe
